md2latex_converter/__init__.py
md2latex_converter/__main__.py
md2latex_converter/cmd_parser.py
md2latex_converter/configurehandler.py
md2latex_converter/error.py
md2latex_converter/helpme.py
md2latex_converter/inline.py
md2latex_converter/inputhandler.py
md2latex_converter/io_handler.py
md2latex_converter/parser.py
md2latex_converter/regexlexer.py
md2latex_converter/sentences.py
md2latex_converter/version.py
md2latex_converter/workflow.py
md2latex_converter/core/__init__.py
md2latex_converter/core/cmd_parser.py
md2latex_converter/core/configure_handler.py
md2latex_converter/core/helpme_handler.py
md2latex_converter/core/inline.py
md2latex_converter/core/io_handler.py
md2latex_converter/core/sentence_parser.py
md2latex_converter/core/tokenizer.py
md2latex_converter/core/workflow.py
md2latex_converter/data_structures/__init__.py
md2latex_converter/data_structures/blk_ext.py
md2latex_converter/data_structures/blocks.py
md2latex_converter/data_structures/prototypes.py
md2latex_converter/data_structures/runtime_maps.py
md2latex_converter/data_structures/sent_ext.py
md2latex_converter/data_structures/sentences.py
md2latex_converter-0.0.7.dist-info/LICENSE.txt
md2latex_converter-0.0.7.dist-info/METADATA
md2latex_converter-0.0.7.dist-info/WHEEL
md2latex_converter-0.0.7.dist-info/entry_points.txt
md2latex_converter-0.0.7.dist-info/top_level.txt
md2latex_converter-0.0.7.dist-info/RECORD
