Metadata-Version: 2.1
Name: md2latex-converter
Version: 0.0.7
Summary: A md-to-LaTeX converter
Author: TrickEye
Author-email: TrickEye@buaa.edu.cn
License: MIT License        
Requires-Python: >=3.10
License-File: LICENSE.txt
Requires-Dist: pyperclip
